{
    "os": "Linux-4.15.0-72-generic-x86_64-with-glibc2.27",
    "python": "3.9.16",
    "heartbeatAt": "2023-08-02T22:23:38.815201",
    "startedAt": "2023-08-02T22:23:37.183841",
    "docker": null,
    "cuda": null,
    "args": [
        "--batch_size",
        "32",
        "--n_workers",
        "8",
        "--epochs",
        "40",
        "--output",
        "model/esb_",
        "--ensemble_number",
        "2",
        "--lr",
        "1e-6"
    ],
    "state": "running",
    "program": "/media/leelabsg-storage1/yein/research/BrainAging/0726_titan/main_cv.py",
    "codePath": "main_cv.py",
    "git": {
        "remote": "git@github.com:yein-hwang/brain_aging.git",
        "commit": "7d9fbb1cde495e17a36f531537b5ff3c99e13666"
    },
    "email": "yein.h.hwang@snu.ac.kr",
    "root": "/media/leelabsg-storage1/yein/research/BrainAging/0726_titan",
    "host": "a09",
    "username": "yeinhwang",
    "executable": "/home/n1/yeinhwang/anaconda3/envs/ba_torch/bin/python",
    "cpu_count": 32,
    "cpu_count_logical": 64,
    "cpu_freq": {
        "current": 0.8195937499999991,
        "min": 800.0,
        "max": 2101.0
    },
    "cpu_freq_per_core": [
        {
            "current": 1.755,
            "min": 800.0,
            "max": 2101.0
        },
        {
            "current": 0.801,
            "min": 800.0,
            "max": 2101.0
        },
        {
            "current": 0.8,
            "min": 800.0,
            "max": 2101.0
        },
        {
            "current": 0.8,
            "min": 800.0,
            "max": 2101.0
        },
        {
            "current": 0.8,
            "min": 800.0,
            "max": 2101.0
        },
        {
            "current": 0.8,
            "min": 800.0,
            "max": 2101.0
        },
        {
            "current": 0.8,
            "min": 800.0,
            "max": 2101.0
        },
        {
            "current": 0.8,
            "min": 800.0,
            "max": 2101.0
        },
        {
            "current": 0.801,
            "min": 800.0,
            "max": 2101.0
        },
        {
            "current": 0.8,
            "min": 800.0,
            "max": 2101.0
        },
        {
            "current": 0.8,
            "min": 800.0,
            "max": 2101.0
        },
        {
            "current": 0.8,
            "min": 800.0,
            "max": 2101.0
        },
        {
            "current": 0.8,
            "min": 800.0,
            "max": 2101.0
        },
        {
            "current": 0.8,
            "min": 800.0,
            "max": 2101.0
        },
        {
            "current": 0.8,
            "min": 800.0,
            "max": 2101.0
        },
        {
            "current": 0.8,
            "min": 800.0,
            "max": 2101.0
        },
        {
            "current": 0.8,
            "min": 800.0,
            "max": 2101.0
        },
        {
            "current": 0.8,
            "min": 800.0,
            "max": 2101.0
        },
        {
            "current": 0.8,
            "min": 800.0,
            "max": 2101.0
        },
        {
            "current": 0.8,
            "min": 800.0,
            "max": 2101.0
        },
        {
            "current": 0.8,
            "min": 800.0,
            "max": 2101.0
        },
        {
            "current": 0.8,
            "min": 800.0,
            "max": 2101.0
        },
        {
            "current": 0.8,
            "min": 800.0,
            "max": 2101.0
        },
        {
            "current": 0.8,
            "min": 800.0,
            "max": 2101.0
        },
        {
            "current": 0.8,
            "min": 800.0,
            "max": 2101.0
        },
        {
            "current": 0.8,
            "min": 800.0,
            "max": 2101.0
        },
        {
            "current": 0.8,
            "min": 800.0,
            "max": 2101.0
        },
        {
            "current": 0.8,
            "min": 800.0,
            "max": 2101.0
        },
        {
            "current": 0.8,
            "min": 800.0,
            "max": 2101.0
        },
        {
            "current": 0.8,
            "min": 800.0,
            "max": 2101.0
        },
        {
            "current": 0.8,
            "min": 800.0,
            "max": 2101.0
        },
        {
            "current": 0.8,
            "min": 800.0,
            "max": 2101.0
        },
        {
            "current": 2.041,
            "min": 800.0,
            "max": 2101.0
        },
        {
            "current": 0.829,
            "min": 800.0,
            "max": 2101.0
        },
        {
            "current": 0.8,
            "min": 800.0,
            "max": 2101.0
        },
        {
            "current": 0.8,
            "min": 800.0,
            "max": 2101.0
        },
        {
            "current": 0.8,
            "min": 800.0,
            "max": 2101.0
        },
        {
            "current": 0.8,
            "min": 800.0,
            "max": 2101.0
        },
        {
            "current": 0.801,
            "min": 800.0,
            "max": 2101.0
        },
        {
            "current": 0.8,
            "min": 800.0,
            "max": 2101.0
        },
        {
            "current": 0.8,
            "min": 800.0,
            "max": 2101.0
        },
        {
            "current": 0.8,
            "min": 800.0,
            "max": 2101.0
        },
        {
            "current": 0.8,
            "min": 800.0,
            "max": 2101.0
        },
        {
            "current": 0.8,
            "min": 800.0,
            "max": 2101.0
        },
        {
            "current": 0.8,
            "min": 800.0,
            "max": 2101.0
        },
        {
            "current": 0.8,
            "min": 800.0,
            "max": 2101.0
        },
        {
            "current": 0.8,
            "min": 800.0,
            "max": 2101.0
        },
        {
            "current": 0.8,
            "min": 800.0,
            "max": 2101.0
        },
        {
            "current": 0.8,
            "min": 800.0,
            "max": 2101.0
        },
        {
            "current": 0.8,
            "min": 800.0,
            "max": 2101.0
        },
        {
            "current": 0.8,
            "min": 800.0,
            "max": 2101.0
        },
        {
            "current": 0.8,
            "min": 800.0,
            "max": 2101.0
        },
        {
            "current": 0.8,
            "min": 800.0,
            "max": 2101.0
        },
        {
            "current": 0.8,
            "min": 800.0,
            "max": 2101.0
        },
        {
            "current": 0.8,
            "min": 800.0,
            "max": 2101.0
        },
        {
            "current": 0.8,
            "min": 800.0,
            "max": 2101.0
        },
        {
            "current": 0.806,
            "min": 800.0,
            "max": 2101.0
        },
        {
            "current": 0.8,
            "min": 800.0,
            "max": 2101.0
        },
        {
            "current": 0.8,
            "min": 800.0,
            "max": 2101.0
        },
        {
            "current": 0.8,
            "min": 800.0,
            "max": 2101.0
        },
        {
            "current": 0.8,
            "min": 800.0,
            "max": 2101.0
        },
        {
            "current": 0.8,
            "min": 800.0,
            "max": 2101.0
        },
        {
            "current": 0.799,
            "min": 800.0,
            "max": 2101.0
        },
        {
            "current": 0.8,
            "min": 800.0,
            "max": 2101.0
        }
    ],
    "disk": {
        "total": 228.22814559936523,
        "used": 22.32778549194336
    },
    "gpu": "NVIDIA TITAN RTX",
    "gpu_count": 4,
    "gpu_devices": [
        {
            "name": "NVIDIA TITAN RTX",
            "memory_total": 25396838400
        },
        {
            "name": "NVIDIA TITAN RTX",
            "memory_total": 25396838400
        },
        {
            "name": "NVIDIA TITAN RTX",
            "memory_total": 25396838400
        },
        {
            "name": "NVIDIA TITAN RTX",
            "memory_total": 25396838400
        }
    ],
    "memory": {
        "total": 502.571475982666
    }
}
